{
  "1": {
    "code": "01.00.00",
    "title": "Математика и механика"
  },
  "2": {
    "code": "02.00.00",
    "title": "Компьютерные и информационные науки"
  },
  "3": {
    "code": "03.00.00",
    "title": "Физика и астрономия"
  },
  "4": {
    "code": "04.00.00",
    "title": "Химия"
  },
  "5": {
    "code": "05.00.00",
    "title": "Науки о земле"
  },
  "6": {
    "code": "06.00.00",
    "title": "Биологические науки"
  },
  "7": {
    "code": "37.00.00",
    "title": "Психологические науки"
  },
  "8": {
    "code": "38.00.00",
    "title": "Экономика и управление"
  },
  "9": {
    "code": "39.00.00",
    "title": "Социология и социальная работа"
  },
  "10": {
    "code": "40.00.00",
    "title": "Юриспруденция"
  },
  "11": {
    "code": "41.00.00",
    "title": "Политические науки и регионоведение"
  },
  "12": {
    "code": "42.00.00",
    "title": "Средства массовой информации и информационно-библиотечное дело"
  },
  "13": {
    "code": "43.00.00",
    "title": "Сервис и туризм"
  },
  "14": {
    "code": "50.00.00",
    "title": "Искусствознание"
  },
  "15": {
    "code": "51.00.00",
    "title": "Культуроведение и социокультурные проекты"
  },
  "16": {
    "code": "52.00.00",
    "title": "Сценические искусства и литературное творчество"
  },
  "17": {
    "code": "53.00.00",
    "title": "Музыкальное искусство"
  },
  "18": {
    "code": "54.00.00",
    "title": "Изобразительное и прикладные виды искусств"
  },
  "19": {
    "code": "45.00.00",
    "title": "Языкознание и литературоведение"
  },
  "20": {
    "code": "46.00.00",
    "title": "История и археология"
  },
  "21": {
    "code": "47.00.00",
    "title": "Философия, этика и религиоведение"
  },
  "22": {
    "code": "48.00.00",
    "title": "Теология"
  },
  "23": {
    "code": "49.00.00",
    "title": "Физическая культура и спорт"
  },
  "24": {
    "code": "07.00.00",
    "title": "Архитектура"
  },
  "25": {
    "code": "08.00.00",
    "title": "Техника и технологии строительства"
  },
  "26": {
    "code": "09.00.00",
    "title": "Информатика и вычислительная техника"
  },
  "27": {
    "code": "10.00.00",
    "title": "Информационная безопасность"
  },
  "28": {
    "code": "11.00.00",
    "title": "Электроника, радиотехника и системы связи"
  },
  "29": {
    "code": "12.00.00",
    "title": "Фотоника, приборостроение, оптические и биотехнические системы и технологии"
  },
  "30": {
    "code": "13.00.00",
    "title": "Электро- и теплоэнергетика"
  },
  "31": {
    "code": "14.00.00",
    "title": "Ядерная энергетика и технологии"
  },
  "32": {
    "code": "15.00.00",
    "title": "Машиностроение"
  },
  "33": {
    "code": "16.00.00",
    "title": "Физико-технические науки и технологии"
  },
  "34": {
    "code": "17.00.00",
    "title": "Оружие и системы вооружения"
  },
  "35": {
    "code": "18.00.00",
    "title": "Химические технологии"
  },
  "36": {
    "code": "19.00.00",
    "title": "Промышленная экология и биотехнологии"
  },
  "37": {
    "code": "20.00.00",
    "title": "Техносферная безопасность и природообустройство"
  },
  "38": {
    "code": "21.00.00",
    "title": "Прикладная геология, горное дело, нефтегазовое дело и геодезия"
  },
  "39": {
    "code": "22.00.00",
    "title": "Технологии материалов"
  },
  "40": {
    "code": "23.00.00",
    "title": "Техника и технологии наземного транспорта"
  },
  "41": {
    "code": "24.00.00",
    "title": "Авиационная и ракетно-космическая техника"
  },
  "42": {
    "code": "25.00.00",
    "title": "Аэронавигация и эксплуатация авиационной и ракетно-космической техники"
  },
  "43": {
    "code": "26.00.00",
    "title": "Техника и технологии кораблестроения и водного транспорта"
  },
  "44": {
    "code": "27.00.00",
    "title": "Управление в технических системах"
  },
  "45": {
    "code": "28.00.00",
    "title": "Нанотехнологии и наноматериалы"
  },
  "46": {
    "code": "29.00.00",
    "title": "Технологии легкой промышленности"
  },
  "47": {
    "code": "34.00.00",
    "title": "Сестринское дело"
  },
  "48": {
    "code": "44.00.00",
    "title": "Образование и педагогические науки"
  },
  "49": {
    "code": "35.00.00",
    "title": "Сельское, лесное и рыбное хозяйство"
  },
  "50": {
    "code": "36.00.00",
    "title": "Ветеринария и зоотехния"
  },
  "52": {
    "code": "39.03.01",
    "title": "Социология"
  },
  "53": {
    "code": "41.03.05",
    "title": "Международные отношения"
  },
  "54": {
    "code": "51.06.01",
    "title": "Культурология"
  },
  "55": {
    "code": "41.03.03",
    "title": "Востоковедение и африканистика"
  },
  "56": {
    "code": "38.03.05",
    "title": "Бизнес-информатика"
  },
  "57": {
    "code": "38.03.04",
    "title": "Государственное и муниципальное управление"
  },
  "58": {
    "code": "07.04.04",
    "title": "Градостроительство"
  },
  "59": {
    "code": "09.03.01",
    "title": "Информатика и вычислительная техника"
  },
  "60": {
    "code": "38.03.02",
    "title": "Менеджмент"
  },
  "61": {
    "code": "38.03.01",
    "title": "Экономика"
  },
  "62": {
    "code": "27.04.02",
    "title": "Управление качеством"
  },
  "63": {
    "code": "42.03.01",
    "title": "Реклама и связи с общественностью"
  },
  "64": {
    "code": "39.00.01",
    "title": "Социология"
  },
  "65": {
    "code": "54.03.01",
    "title": "Дизайн"
  },
  "66": {
    "code": "41.03.04",
    "title": "Политология"
  },
  "67": {
    "code": "40.03.01",
    "title": "Юриспруденция"
  },
  "68": {
    "code": "37.03.01",
    "title": "Психология"
  },
  "69": {
    "code": "38.03.00",
    "title": "Менеджмент"
  },
  "72": {
    "code": "03.02.00",
    "title": "Политология"
  },
  "73": {
    "code": "03.19.00",
    "title": "Международные отношения"
  },
  "74": {
    "code": "03.16.00",
    "title": "Реклама и связи с общественностью"
  },
  "75": {
    "code": "03.40.00",
    "title": "Конфликтология"
  },
  "76": {
    "code": "44.04.02  ",
    "title": "Психолого-педагогическое образование"
  },
  "77": {
    "code": "08.02.00",
    "title": "Менеджмент"
  },
  "79": {
    "code": "42.03.02",
    "title": "Журналистика"
  },
  "80": {
    "code": "42.04.05",
    "title": "Медиакоммуникации"
  },
  "81": {
    "code": "42.04.01",
    "title": "Реклама и связи с общественностью"
  },
  "82": {
    "code": "41.03.06",
    "title": "Публичная политика и социальные науки"
  },
  "83": {
    "code": "39.04.01",
    "title": "Социология"
  },
  "84": {
    "code": "42.04.02",
    "title": "Журналистика"
  },
  "88": {
    "code": "38.04.01",
    "title": "Экономика"
  },
  "90": {
    "code": "01.03.04",
    "title": "Прикладная математика"
  },
  "91": {
    "code": "47.03.01",
    "title": "Философия"
  },
  "93": {
    "code": "46.03.01",
    "title": "История"
  },
  "95": {
    "code": "41.03.01",
    "title": "Зарубежное регионоведение"
  },
  "97": {
    "code": "01.03.00",
    "title": "Математика. Компьютерные науки"
  },
  "98": {
    "code": "05.03.01",
    "title": "Геология"
  },
  "99": {
    "code": "03.03.00",
    "title": "Психология"
  },
  "100": {
    "code": "04.03.00",
    "title": "Конфликтология"
  },
  "101": {
    "code": "08.03.00",
    "title": "Коммерция"
  },
  "102": {
    "code": "40.06.01",
    "title": "Юриспруденция"
  },
  "104": {
    "code": "38.03.03",
    "title": "Управление персоналом"
  },
  "105": {
    "code": "13.03.03",
    "title": "Энергетическое машиностроение"
  },
  "107": {
    "code": "15.03.03 ",
    "title": "Прикладная механика"
  },
  "108": {
    "code": "15.03.05",
    "title": "Конструкторско-технологическое обеспечение машиностроительных производств"
  },
  "109": {
    "code": "15.03.04 ",
    "title": "Автоматизация технологических процессов и производств"
  },
  "110": {
    "code": "38.06.01",
    "title": "Экономика"
  },
  "113": {
    "code": "02.04.01",
    "title": "Математика и компьютерные науки"
  },
  "120": {
    "code": "15.03.02",
    "title": "Технологические машины и оборудование"
  },
  "121": {
    "code": "08.00.10",
    "title": "Финансы, денежное обращение и кредит"
  },
  "122": {
    "code": "08.00.05",
    "title": "Экономика, управление народным хозяйством"
  },
  "123": {
    "code": "01.03.01",
    "title": "Математика"
  },
  "125": {
    "code": "22.04.01",
    "title": "Материаловедение и технологии материалов"
  },
  "126": {
    "code": "28.03.03",
    "title": "Наноматериалы"
  },
  "127": {
    "code": "27.03.04",
    "title": "Управление в технических системах"
  },
  "128": {
    "code": "27.04.04",
    "title": "Управление в технических системах"
  },
  "129": {
    "code": "14.04.00",
    "title": "Энергетика и электротехника"
  },
  "130": {
    "code": "30.00.00",
    "title": "Фундаментальная медицина"
  },
  "131": {
    "code": "31.00.00",
    "title": "Клиническая медицина"
  },
  "132": {
    "code": "32.00.00",
    "title": "Науки о здоровье и профилактическая медицина"
  },
  "133": {
    "code": "33.00.00",
    "title": "Фармация"
  },
  "134": {
    "code": "55.00.00",
    "title": "Экранные искусства"
  },
  "135": {
    "code": "24.03.02",
    "title": "Системы управления движением и навигация"
  },
  "136": {
    "code": "10.03.01",
    "title": "Информационная безопасность"
  },
  "137": {
    "code": "02.03.01",
    "title": "Математика и компьютерные науки"
  },
  "139": {
    "code": "13.00.02",
    "title": "Теория и методика обучения и воспитания"
  },
  "140": {
    "code": "09.03.02",
    "title": "Информационные системы и технологии"
  },
  "141": {
    "code": "09.04.02",
    "title": "Информационные системы и технологии"
  },
  "142": {
    "code": "12.03.01",
    "title": "Приборостроение"
  },
  "143": {
    "code": "45.03.01",
    "title": "Филология"
  },
  "144": {
    "code": "45.03.02",
    "title": "Лингвистика"
  },
  "145": {
    "code": "45.03.03",
    "title": "Фундаментальная и прикладная лингвистика"
  },
  "146": {
    "code": "45.03.04",
    "title": "Интеллектуальные системы в гуманитарной сфере"
  },
  "147": {
    "code": "44.03.01",
    "title": "Педагогическое образование"
  },
  "148": {
    "code": "09.03.04",
    "title": "Программная инженерия"
  },
  "149": {
    "code": "09.03.03",
    "title": "Прикладная информатика"
  },
  "150": {
    "code": "27.03.05",
    "title": "Инноватика"
  },
  "151": {
    "code": "11.03.02",
    "title": "Инфокоммуникационные технологии и системы связи"
  },
  "152": {
    "code": "03.04.02",
    "title": "Физика"
  },
  "153": {
    "code": "03.05.01",
    "title": "Астрономия"
  },
  "154": {
    "code": "04.03.01",
    "title": "Химия"
  },
  "155": {
    "code": "04.03.02",
    "title": "Химия, физика и механика материалов"
  },
  "156": {
    "code": "04.05.01",
    "title": "Фундаментальная и прикладная химия"
  },
  "159": {
    "code": "02.03.02",
    "title": "Фундаментальная информатика и информационные технологии"
  },
  "160": {
    "code": "10.05.01",
    "title": "Компьютерная безопасность"
  },
  "161": {
    "code": "01.03.02",
    "title": "Прикладная математика и информатика"
  },
  "162": {
    "code": "01.03.03",
    "title": "Механика и математическое моделирование"
  },
  "164": {
    "code": "02.03.03",
    "title": "Математическое обеспечение и администрирование информационных систем"
  },
  "165": {
    "code": "01.04.02",
    "title": "Прикладная математика и информатика"
  },
  "166": {
    "code": "11.03.01",
    "title": "Радиотехника"
  },
  "167": {
    "code": "11.03.03",
    "title": "Конструирование и технология электронных средств"
  },
  "168": {
    "code": "11.03.04",
    "title": "Электроника и наноэлектроника"
  },
  "170": {
    "code": "02.04.03",
    "title": "Математическое обеспечение и администрирование информационных систем"
  },
  "171": {
    "code": "20.03.01",
    "title": "Техносферная безопасность"
  },
  "172": {
    "code": "05.03.06",
    "title": "Экология и природопользование"
  },
  "173": {
    "code": "06.03.01",
    "title": "Биология"
  },
  "174": {
    "code": "08.03.01",
    "title": "Строительство"
  },
  "175": {
    "code": "12.03.04",
    "title": "Биотехнические системы и технологии"
  },
  "176": {
    "code": "35.03.07",
    "title": "Технология производства и переработки сельскохозяйственной продукции"
  },
  "177": {
    "code": "01.03.05",
    "title": "Статистика"
  },
  "178": {
    "code": "01.04.04",
    "title": "Прикладная математика"
  },
  "179": {
    "code": "02.04.02",
    "title": "Фундаментальная информатика и информационные технологии"
  },
  "180": {
    "code": "09.04.03",
    "title": "Прикладная информатика"
  },
  "181": {
    "code": "10.04.01",
    "title": "Информационная безопасность"
  },
  "182": {
    "code": "45.06.01",
    "title": "Языкознание и литературоведение"
  },
  "183": {
    "code": "03.03.02",
    "title": "Физика"
  },
  "184": {
    "code": "05.03.02",
    "title": "География"
  },
  "185": {
    "code": "41.06.01",
    "title": "Политические науки и регионоведение"
  },
  "186": {
    "code": "47.06.01",
    "title": "Философия, этика и религиоведение"
  },
  "187": {
    "code": "48.06.01",
    "title": "Теология"
  },
  "188": {
    "code": "37.06.01",
    "title": "Психологические науки"
  },
  "189": {
    "code": "39.06.01",
    "title": "Социологические науки"
  },
  "190": {
    "code": "42.06.01",
    "title": "Средства массовой информации и информационно-библиотечное дело"
  },
  "191": {
    "code": "44.06.01",
    "title": "Образование и педагогические науки"
  },
  "192": {
    "code": "46.06.01",
    "title": "Исторические науки и археология"
  },
  "193": {
    "code": "50.06.01",
    "title": "Искусствоведение"
  },
  "194": {
    "code": "04.06.01",
    "title": "Химические науки"
  },
  "195": {
    "code": "05.06.01",
    "title": "Науки о Земле"
  },
  "196": {
    "code": "01.04.01",
    "title": "Математика"
  },
  "197": {
    "code": "09.04.04",
    "title": "Программная инженерия"
  },
  "198": {
    "code": "01.06.01",
    "title": "Математика и механика"
  },
  "199": {
    "code": "03.06.01",
    "title": "Физика и астрономия"
  },
  "200": {
    "code": "15.03.06",
    "title": "Мехатроника и робототехника"
  },
  "201": {
    "code": "15.03.01",
    "title": "Машиностроение"
  },
  "202": {
    "code": "23.03.03",
    "title": "Эксплуатация транспортно- технологических машин и комплексов"
  },
  "203": {
    "code": "35.03.02",
    "title": "Технология лесозаготовительных и деревоперерабатывающих производств"
  },
  "204": {
    "code": "24.03.05",
    "title": "Двигатели летательных аппаратов"
  },
  "205": {
    "code": "05.03.04",
    "title": "Гидрометеорология"
  },
  "206": {
    "code": "06.06.01",
    "title": "Биологические науки"
  },
  "207": {
    "code": "30.06.01",
    "title": "Фундаментальная медицина"
  },
  "208": {
    "code": "31.06.01",
    "title": "Клиническая медицина"
  },
  "209": {
    "code": "32.06.01",
    "title": "Медико-профилактическое дело"
  },
  "210": {
    "code": "33.06.01",
    "title": "Фармация"
  },
  "211": {
    "code": "35.06.01",
    "title": "Сельское хозяйство"
  },
  "212": {
    "code": "35.06.02",
    "title": "Лесное хозяйство"
  },
  "213": {
    "code": "35.06.03",
    "title": "Рыбное хозяйство"
  },
  "214": {
    "code": "35.06.04",
    "title": "Технологии, средства механизации и энергетическое оборудование в сельском, лесном и рыбном хозяйстве"
  },
  "215": {
    "code": "36.06.01",
    "title": "Ветеринария и зоотехния"
  },
  "216": {
    "code": "49.06.01",
    "title": "Физическая культура и спорт"
  },
  "217": {
    "code": "02.06.01",
    "title": "Компьютерные и информационные науки"
  },
  "218": {
    "code": "07.06.01",
    "title": "Архитектура"
  },
  "219": {
    "code": "08.06.01",
    "title": "Техника и технологии строительства"
  },
  "220": {
    "code": "09.06.01",
    "title": "Информатика и вычислительная техника"
  },
  "221": {
    "code": "10.06.01",
    "title": "Информационная безопасность"
  },
  "222": {
    "code": "11.06.01",
    "title": "Электроника, радиотехника и системы связи"
  },
  "223": {
    "code": "12.06.01",
    "title": "Фотоника, приборостроение, оптические и биотехнические системы и технологии"
  },
  "224": {
    "code": "13.06.01",
    "title": "Электро- и теплотехника"
  },
  "225": {
    "code": "14.06.01",
    "title": "Ядерная, тепловая и возобновляемая энергетика и сопутствующие технологии"
  },
  "226": {
    "code": "15.06.01",
    "title": "Машиностроение"
  },
  "227": {
    "code": "16.06.01",
    "title": "Физико-технические науки и технологии"
  },
  "228": {
    "code": "18.06.01",
    "title": "Химическая технология "
  },
  "229": {
    "code": "19.06.01",
    "title": "Промышленная экология и биотехнологии"
  },
  "230": {
    "code": "20.06.01",
    "title": "Техносферная безопасность"
  },
  "231": {
    "code": "21.06.01",
    "title": "Геология, разведка и разработка полезных ископаемых"
  },
  "232": {
    "code": "21.06.02",
    "title": "Геодезия"
  },
  "233": {
    "code": "22.06.01",
    "title": "Технологии материалов"
  },
  "234": {
    "code": "23.06.01",
    "title": "Техника и технологии наземного транспорта"
  },
  "235": {
    "code": "24.06.01",
    "title": "Авиационная и ракетно-космическая техника"
  },
  "236": {
    "code": "25.06.01",
    "title": "Аэронавигация и эксплуатация авиационной и ракетно-космической техники"
  },
  "237": {
    "code": "26.06.01",
    "title": "Техника и технологии кораблестроения и водного транспорта"
  },
  "238": {
    "code": "27.06.01",
    "title": "Управление в технических системах"
  },
  "239": {
    "code": "28.06.01",
    "title": "Нанотехнологии и наноматериалы"
  },
  "240": {
    "code": "29.06.01",
    "title": "Технологии легкой промышленности"
  },
  "241": {
    "code": "37.05.01",
    "title": "Клиническая психология"
  },
  "242": {
    "code": "37.04.02",
    "title": "Конфликтология"
  },
  "243": {
    "code": "39.03.03",
    "title": "Организация работы с молодежью"
  },
  "244": {
    "code": "44.03.02",
    "title": "Психолого-педагогическое образование"
  },
  "245": {
    "code": "44.03.04",
    "title": "Профессиональное обучение (по отраслям) "
  },
  "246": {
    "code": "44.05.01",
    "title": "Педагогика и психология девиантного поведения"
  },
  "247": {
    "code": "37.04.01",
    "title": "Психология "
  },
  "248": {
    "code": "39.03.02",
    "title": "Социальная работа"
  },
  "249": {
    "code": "49.03.03",
    "title": "Рекреация и спортивно- оздоровительный туризм"
  },
  "250": {
    "code": "54.05.03",
    "title": "Графика"
  },
  "251": {
    "code": "27.04.05",
    "title": "Инноватика"
  },
  "252": {
    "code": "38.04.02",
    "title": "Менеджмент"
  },
  "253": {
    "code": "38.04.03",
    "title": "Управление персоналом"
  },
  "254": {
    "code": "38.04.04",
    "title": "Государственное и муниципальное управление"
  },
  "255": {
    "code": "39.04.03",
    "title": "Организация работы с молодежью "
  },
  "256": {
    "code": "39.04.02",
    "title": "Социальная работа"
  },
  "257": {
    "code": "41.04.04",
    "title": "Политология"
  },
  "258": {
    "code": "41.04.05",
    "title": "Международные отношения"
  },
  "259": {
    "code": "54.04.01",
    "title": "Дизайн"
  },
  "260": {
    "code": "47.04.01",
    "title": "Философия"
  },
  "261": {
    "code": "35.03.04",
    "title": "Агрономия"
  }
}